crdb/__init__.py
crdb/__main__.py
crdb/cli.py
crdb/core.py
crdb/crdb_logo.png
crdb/experimental.py
crdb/mpl.py
crdb/solarsystem_abundances2003.dat
crdb/units.py
crdb-0.12.0.dist-info/AUTHORS.rst
crdb-0.12.0.dist-info/LICENSE
crdb-0.12.0.dist-info/METADATA
crdb-0.12.0.dist-info/WHEEL
crdb-0.12.0.dist-info/entry_points.txt
crdb-0.12.0.dist-info/top_level.txt
crdb-0.12.0.dist-info/RECORD
